[
    {
        "id": "fa36998f194a0113",
        "type": "tab",
        "label": "Flow House Temps",
        "disabled": false,
        "info": "",
        "env": []
    },
    {
        "id": "388527266ba91c79",
        "type": "tab",
        "label": "Flow House Energy 1",
        "disabled": false,
        "info": "",
        "env": []
    },
    {
        "id": "3401649474d49109",
        "type": "mqtt-broker",
        "name": "ts-vultr",
        "broker": "vultr1",
        "port": "1883",
        "clientid": "",
        "autoConnect": true,
        "usetls": false,
        "protocolVersion": "4",
        "keepalive": "60",
        "cleansession": true,
        "autoUnsubscribe": true,
        "birthTopic": "",
        "birthQos": "0",
        "birthRetain": "false",
        "birthPayload": "",
        "birthMsg": {},
        "closeTopic": "",
        "closeQos": "0",
        "closeRetain": "false",
        "closePayload": "",
        "closeMsg": {},
        "willTopic": "",
        "willQos": "0",
        "willRetain": "false",
        "willPayload": "",
        "willMsg": {},
        "userProps": "",
        "sessionExpiry": ""
    },
    {
        "id": "976a565a31995234",
        "type": "ui_group",
        "name": "LIVING ROOM",
        "tab": "f9addb30539f63a3",
        "order": 4,
        "disp": true,
        "width": "6",
        "collapse": false,
        "className": ""
    },
    {
        "id": "cf2742497e042c41",
        "type": "ui_group",
        "name": "PATIO",
        "tab": "f9addb30539f63a3",
        "order": 2,
        "disp": true,
        "width": "6",
        "collapse": false,
        "className": ""
    },
    {
        "id": "a769dc138a6597bb",
        "type": "ui_group",
        "name": "SHRINE ROOM",
        "tab": "f9addb30539f63a3",
        "order": 1,
        "disp": true,
        "width": "6",
        "collapse": false,
        "className": ""
    },
    {
        "id": "f9addb30539f63a3",
        "type": "ui_tab",
        "name": "House Temps All Up",
        "icon": "dashboard",
        "order": 5,
        "disabled": false,
        "hidden": false
    },
    {
        "id": "c00570e053d879d0",
        "type": "ui_base",
        "theme": {
            "name": "theme-dark",
            "lightTheme": {
                "default": "#0094CE",
                "baseColor": "#0094CE",
                "baseFont": "-apple-system,BlinkMacSystemFont,Segoe UI,Roboto,Oxygen-Sans,Ubuntu,Cantarell,Helvetica Neue,sans-serif",
                "edited": true,
                "reset": false
            },
            "darkTheme": {
                "default": "#097479",
                "baseColor": "#097479",
                "baseFont": "-apple-system,BlinkMacSystemFont,Segoe UI,Roboto,Oxygen-Sans,Ubuntu,Cantarell,Helvetica Neue,sans-serif",
                "edited": true,
                "reset": false
            },
            "customTheme": {
                "name": "Untitled Theme 1",
                "default": "#4B7930",
                "baseColor": "#4B7930",
                "baseFont": "-apple-system,BlinkMacSystemFont,Segoe UI,Roboto,Oxygen-Sans,Ubuntu,Cantarell,Helvetica Neue,sans-serif"
            },
            "themeState": {
                "base-color": {
                    "default": "#097479",
                    "value": "#097479",
                    "edited": false
                },
                "page-titlebar-backgroundColor": {
                    "value": "#097479",
                    "edited": false
                },
                "page-backgroundColor": {
                    "value": "#111111",
                    "edited": false
                },
                "page-sidebar-backgroundColor": {
                    "value": "#333333",
                    "edited": false
                },
                "group-textColor": {
                    "value": "#0eb8c0",
                    "edited": false
                },
                "group-borderColor": {
                    "value": "#555555",
                    "edited": false
                },
                "group-backgroundColor": {
                    "value": "#333333",
                    "edited": false
                },
                "widget-textColor": {
                    "value": "#eeeeee",
                    "edited": false
                },
                "widget-backgroundColor": {
                    "value": "#097479",
                    "edited": false
                },
                "widget-borderColor": {
                    "value": "#333333",
                    "edited": false
                },
                "base-font": {
                    "value": "-apple-system,BlinkMacSystemFont,Segoe UI,Roboto,Oxygen-Sans,Ubuntu,Cantarell,Helvetica Neue,sans-serif"
                }
            },
            "angularTheme": {
                "primary": "indigo",
                "accents": "blue",
                "warn": "red",
                "background": "grey",
                "palette": "light"
            }
        },
        "site": {
            "name": "Node-RED Dashboard",
            "hideToolbar": "false",
            "allowSwipe": "false",
            "lockMenu": "false",
            "allowTempTheme": "true",
            "dateFormat": "DD/MM/YYYY",
            "sizes": {
                "sx": 48,
                "sy": 48,
                "gx": 6,
                "gy": 6,
                "cx": 6,
                "cy": 6,
                "px": 0,
                "py": 0
            }
        }
    },
    {
        "id": "a7d03dcb5b95e73e",
        "type": "ui_group",
        "name": "PORCH",
        "tab": "f9addb30539f63a3",
        "order": 3,
        "disp": true,
        "width": "6",
        "collapse": false,
        "className": ""
    },
    {
        "id": "274e18a98dc98d5f",
        "type": "mqtt-broker",
        "name": "n-vultr",
        "broker": "n-vultr1",
        "port": "1883",
        "clientid": "",
        "autoConnect": true,
        "usetls": false,
        "protocolVersion": "4",
        "keepalive": "60",
        "cleansession": true,
        "autoUnsubscribe": true,
        "birthTopic": "",
        "birthQos": "0",
        "birthRetain": "false",
        "birthPayload": "",
        "birthMsg": {},
        "closeTopic": "",
        "closeQos": "0",
        "closeRetain": "false",
        "closePayload": "",
        "closeMsg": {},
        "willTopic": "",
        "willQos": "0",
        "willRetain": "false",
        "willPayload": "",
        "willMsg": {},
        "userProps": "",
        "sessionExpiry": ""
    },
    {
        "id": "40227b344b006862",
        "type": "mqtt-broker",
        "name": "n-vutlr1",
        "broker": "149.28.196.72",
        "port": "1883",
        "clientid": "ktbcs_mbp_node-red",
        "autoConnect": true,
        "usetls": false,
        "protocolVersion": "4",
        "keepalive": "60",
        "cleansession": true,
        "autoUnsubscribe": true,
        "birthTopic": "",
        "birthQos": "0",
        "birthRetain": "false",
        "birthPayload": "",
        "birthMsg": {},
        "closeTopic": "",
        "closeQos": "0",
        "closeRetain": "false",
        "closePayload": "",
        "closeMsg": {},
        "willTopic": "",
        "willQos": "0",
        "willRetain": "false",
        "willPayload": "",
        "willMsg": {},
        "userProps": "",
        "sessionExpiry": ""
    },
    {
        "id": "551fa096c4be3b6d",
        "type": "ui_group",
        "name": "Lab Charts",
        "tab": "cfd079416572a5a1",
        "order": 1,
        "disp": false,
        "width": 5,
        "collapse": false,
        "className": ""
    },
    {
        "id": "b0aff1d8906e664d",
        "type": "ui_group",
        "name": "Prod Charts",
        "tab": "cfd079416572a5a1",
        "order": 3,
        "disp": false,
        "width": 5,
        "collapse": false,
        "className": ""
    },
    {
        "id": "83a2dcafa4b40858",
        "type": "ui_group",
        "name": "EV Charts",
        "tab": "cfd079416572a5a1",
        "order": 5,
        "disp": false,
        "width": "5",
        "collapse": false,
        "className": ""
    },
    {
        "id": "342e62fb87e28291",
        "type": "ui_group",
        "name": "Lab Guages",
        "tab": "cfd079416572a5a1",
        "order": 2,
        "disp": false,
        "width": 5,
        "collapse": false,
        "className": ""
    },
    {
        "id": "0120b7d51f39933f",
        "type": "ui_group",
        "name": "Prod Guages",
        "tab": "cfd079416572a5a1",
        "order": 4,
        "disp": false,
        "width": 5,
        "collapse": false,
        "className": ""
    },
    {
        "id": "d0e6d933f5c08d05",
        "type": "ui_group",
        "name": "EV Guages",
        "tab": "cfd079416572a5a1",
        "order": 6,
        "disp": false,
        "width": 5,
        "collapse": false,
        "className": ""
    },
    {
        "id": "cfd079416572a5a1",
        "type": "ui_tab",
        "name": "SmartPlug_Dashboard",
        "icon": "dashboard",
        "disabled": false,
        "hidden": false
    },
    {
        "id": "768c16f829254130",
        "type": "ui_spacer",
        "z": "388527266ba91c79",
        "name": "spacer",
        "group": "551fa096c4be3b6d",
        "order": 3,
        "width": 5,
        "height": 1
    },
    {
        "id": "5c25f8002e2f40c2",
        "type": "ui_spacer",
        "z": "388527266ba91c79",
        "name": "spacer",
        "group": "551fa096c4be3b6d",
        "order": 5,
        "width": 5,
        "height": 1
    },
    {
        "id": "64d95a24f1056cb2",
        "type": "ui_spacer",
        "z": "388527266ba91c79",
        "name": "spacer",
        "group": "551fa096c4be3b6d",
        "order": 7,
        "width": 5,
        "height": 1
    },
    {
        "id": "f114a87eb2514230",
        "type": "ui_spacer",
        "z": "388527266ba91c79",
        "name": "spacer",
        "group": "b0aff1d8906e664d",
        "order": 3,
        "width": 5,
        "height": 1
    },
    {
        "id": "8476ed064ae2a8c5",
        "type": "ui_spacer",
        "z": "388527266ba91c79",
        "name": "spacer",
        "group": "b0aff1d8906e664d",
        "order": 5,
        "width": 5,
        "height": 1
    },
    {
        "id": "fdad94fcbb1efcf0",
        "type": "ui_spacer",
        "z": "388527266ba91c79",
        "name": "spacer",
        "group": "b0aff1d8906e664d",
        "order": 7,
        "width": 5,
        "height": 1
    },
    {
        "id": "a36b529aa1a68e3e",
        "type": "ui_spacer",
        "z": "388527266ba91c79",
        "name": "spacer",
        "group": "83a2dcafa4b40858",
        "order": 3,
        "width": 5,
        "height": 1
    },
    {
        "id": "c759ea62e4498bc1",
        "type": "ui_spacer",
        "z": "388527266ba91c79",
        "name": "spacer",
        "group": "83a2dcafa4b40858",
        "order": 5,
        "width": 5,
        "height": 1
    },
    {
        "id": "3c992c2a633fd656",
        "type": "ui_spacer",
        "z": "388527266ba91c79",
        "name": "spacer",
        "group": "83a2dcafa4b40858",
        "order": 7,
        "width": 5,
        "height": 1
    },
    {
        "id": "9825e567a1bc01e6",
        "type": "mqtt in",
        "z": "fa36998f194a0113",
        "name": "Vultr1_KTB-MBP_house_weather_sensors",
        "topic": "KTBMES/KTB_MBP/sensors/house_weather_sensors/#",
        "qos": "2",
        "datatype": "auto-detect",
        "broker": "274e18a98dc98d5f",
        "nl": false,
        "rap": true,
        "rh": 0,
        "inputs": 0,
        "x": 180,
        "y": 400,
        "wires": [
            [
                "31770becaf8d443b",
                "22c788cce72a7204",
                "261066bba771706e",
                "2ad7c3d9ed7ce95b"
            ]
        ]
    },
    {
        "id": "31770becaf8d443b",
        "type": "debug",
        "z": "fa36998f194a0113",
        "name": "MQTT Full Payload",
        "active": true,
        "tosidebar": true,
        "console": false,
        "tostatus": false,
        "complete": "payload",
        "targetType": "msg",
        "statusVal": "",
        "statusType": "auto",
        "x": 590,
        "y": 320,
        "wires": []
    },
    {
        "id": "22c788cce72a7204",
        "type": "function",
        "z": "fa36998f194a0113",
        "name": "get_name_and_temperature",
        "func": "msg.payload = {\n    device_name: msg.payload.device_name,\n    temperature_F: msg.payload.temperature_F\n};\nreturn msg;\n",
        "outputs": 1,
        "timeout": 0,
        "noerr": 0,
        "initialize": "",
        "finalize": "",
        "libs": [],
        "x": 580,
        "y": 400,
        "wires": [
            [
                "ca1c9f1c0233ef17",
                "319d6c53a1c19965"
            ]
        ]
    },
    {
        "id": "ca1c9f1c0233ef17",
        "type": "debug",
        "z": "fa36998f194a0113",
        "name": "Name and Temp",
        "active": false,
        "tosidebar": true,
        "console": false,
        "tostatus": false,
        "complete": "payload",
        "targetType": "msg",
        "statusVal": "",
        "statusType": "auto",
        "x": 1000,
        "y": 400,
        "wires": []
    },
    {
        "id": "319d6c53a1c19965",
        "type": "function",
        "z": "fa36998f194a0113",
        "name": "Parse_into_devices_temperature",
        "func": "if (msg.payload.device_name) {\n    let temp = msg.payload.temperature_F;  // Store temperature first\n    let deviceName = msg.payload.device_name.toUpperCase();  // Convert to uppercase\n    msg.payload = temp;\n\n    switch (deviceName) {\n        case \"LIVINGROOM-C\":\n            return [msg, null, null, null];\n        case \"PATIO-B\":\n            return [null, msg, null, null];\n        case \"SHRINEROOM-A\":\n            return [null, null, msg, null];\n        case \"PORCH-B\":\n            return [null, null, null, msg];\n    }\n}\nreturn null;\n\n",
        "outputs": 4,
        "timeout": 0,
        "noerr": 0,
        "initialize": "",
        "finalize": "",
        "libs": [],
        "x": 720,
        "y": 480,
        "wires": [
            [
                "1e1b20ba3515808d",
                "0c0c70c31e140255",
                "70db07855bcba81c"
            ],
            [
                "1e1b20ba3515808d",
                "2e206a0e511fc6c4",
                "66ad9862b4b02d2b"
            ],
            [
                "1e1b20ba3515808d",
                "b7ce9901db11afa1",
                "dba67b839370dd51"
            ],
            [
                "1e1b20ba3515808d",
                "5377c35b6eb21fc9",
                "09b713249c6b4021"
            ]
        ]
    },
    {
        "id": "1e1b20ba3515808d",
        "type": "debug",
        "z": "fa36998f194a0113",
        "name": "Gauge and Chart Data",
        "active": false,
        "tosidebar": true,
        "console": false,
        "tostatus": false,
        "complete": "payload",
        "targetType": "msg",
        "statusVal": "",
        "statusType": "auto",
        "x": 1020,
        "y": 440,
        "wires": []
    },
    {
        "id": "0c0c70c31e140255",
        "type": "ui_gauge",
        "z": "fa36998f194a0113",
        "name": "LIVING ROOM TEMP",
        "group": "976a565a31995234",
        "order": 2,
        "width": 6,
        "height": 5,
        "gtype": "gage",
        "title": "Living Room Temperature",
        "label": "degrees F",
        "format": "{{value | number:0}}",
        "min": "32",
        "max": "90",
        "colors": [
            "#574ce6",
            "#55b4dd",
            "#f4aa0b"
        ],
        "seg1": "50",
        "seg2": "75",
        "diff": false,
        "className": "",
        "x": 1060,
        "y": 520,
        "wires": []
    },
    {
        "id": "2e206a0e511fc6c4",
        "type": "ui_gauge",
        "z": "fa36998f194a0113",
        "name": "PATIO-B TEMP",
        "group": "cf2742497e042c41",
        "order": 2,
        "width": 6,
        "height": 5,
        "gtype": "gage",
        "title": "Patio Temperature",
        "label": "degrees F",
        "format": "{{value | number:0}}",
        "min": "32",
        "max": "90",
        "colors": [
            "#574ce6",
            "#55b4dd",
            "#f4aa0b"
        ],
        "seg1": "50",
        "seg2": "75",
        "diff": false,
        "className": "",
        "x": 1040,
        "y": 620,
        "wires": []
    },
    {
        "id": "b7ce9901db11afa1",
        "type": "ui_gauge",
        "z": "fa36998f194a0113",
        "name": "SHRINE ROOM TEMP",
        "group": "a769dc138a6597bb",
        "order": 2,
        "width": 6,
        "height": 5,
        "gtype": "gage",
        "title": "Shrine Room Temperature",
        "label": "degrees F",
        "format": "{{value | number:0}}",
        "min": "32",
        "max": "90",
        "colors": [
            "#574ce6",
            "#55b4dd",
            "#f4aa0b"
        ],
        "seg1": "50",
        "seg2": "75",
        "diff": false,
        "className": "",
        "x": 1060,
        "y": 700,
        "wires": []
    },
    {
        "id": "5377c35b6eb21fc9",
        "type": "ui_gauge",
        "z": "fa36998f194a0113",
        "name": "PORCH TEMP",
        "group": "a7d03dcb5b95e73e",
        "order": 2,
        "width": 6,
        "height": 5,
        "gtype": "gage",
        "title": "Porch Temperature",
        "label": "degrees F",
        "format": "{{value | number:0}}",
        "min": "32",
        "max": "90",
        "colors": [
            "#574ce6",
            "#55b4dd",
            "#f4aa0b"
        ],
        "seg1": "50",
        "seg2": "75",
        "diff": false,
        "className": "",
        "x": 1040,
        "y": 780,
        "wires": []
    },
    {
        "id": "70db07855bcba81c",
        "type": "ui_chart",
        "z": "fa36998f194a0113",
        "name": "LIVING ROOM TEMP",
        "group": "976a565a31995234",
        "order": 3,
        "width": 0,
        "height": 0,
        "label": "Living Room Temperature",
        "chartType": "line",
        "legend": "false",
        "xformat": "HH:mm:ss",
        "interpolate": "linear",
        "nodata": "Awaiting Data",
        "dot": false,
        "ymin": "32",
        "ymax": "90",
        "removeOlder": "12",
        "removeOlderPoints": "",
        "removeOlderUnit": "3600",
        "cutout": 0,
        "useOneColor": false,
        "useUTC": false,
        "colors": [
            "#a039f3",
            "#aec7e8",
            "#ff7f0e",
            "#2ca02c",
            "#98df8a",
            "#d62728",
            "#ff9896",
            "#986ebf",
            "#c5b0d5"
        ],
        "outputs": 1,
        "useDifferentColor": false,
        "className": "",
        "x": 1060,
        "y": 560,
        "wires": [
            []
        ]
    },
    {
        "id": "09b713249c6b4021",
        "type": "ui_chart",
        "z": "fa36998f194a0113",
        "name": "PORCH TEMP",
        "group": "a7d03dcb5b95e73e",
        "order": 3,
        "width": 0,
        "height": 0,
        "label": "Porch Temperature",
        "chartType": "line",
        "legend": "false",
        "xformat": "HH:mm:ss",
        "interpolate": "linear",
        "nodata": "Awaiting Data",
        "dot": false,
        "ymin": "32",
        "ymax": "90",
        "removeOlder": "12",
        "removeOlderPoints": "",
        "removeOlderUnit": "3600",
        "cutout": 0,
        "useOneColor": false,
        "useUTC": false,
        "colors": [
            "#027acf",
            "#aec7e8",
            "#ff7f0e",
            "#2ca02c",
            "#98df8a",
            "#d62728",
            "#ff9896",
            "#986ebf",
            "#c5b0d5"
        ],
        "outputs": 1,
        "useDifferentColor": false,
        "className": "",
        "x": 1040,
        "y": 820,
        "wires": [
            []
        ]
    },
    {
        "id": "dba67b839370dd51",
        "type": "ui_chart",
        "z": "fa36998f194a0113",
        "name": "SHRINE ROOM TEMP",
        "group": "a769dc138a6597bb",
        "order": 3,
        "width": 0,
        "height": 0,
        "label": "ShrineRoom Temperature",
        "chartType": "line",
        "legend": "false",
        "xformat": "HH:mm:ss",
        "interpolate": "linear",
        "nodata": "Awaiting Data",
        "dot": false,
        "ymin": "32",
        "ymax": "90",
        "removeOlder": "12",
        "removeOlderPoints": "",
        "removeOlderUnit": "3600",
        "cutout": 0,
        "useOneColor": false,
        "useUTC": false,
        "colors": [
            "#f6e204",
            "#aec7e8",
            "#ff7f0e",
            "#2ca02c",
            "#98df8a",
            "#d62728",
            "#ff9896",
            "#986ebf",
            "#c5b0d5"
        ],
        "outputs": 1,
        "useDifferentColor": false,
        "className": "",
        "x": 1060,
        "y": 740,
        "wires": [
            []
        ]
    },
    {
        "id": "66ad9862b4b02d2b",
        "type": "ui_chart",
        "z": "fa36998f194a0113",
        "name": "PATIO-B TEMP",
        "group": "cf2742497e042c41",
        "order": 3,
        "width": 0,
        "height": 0,
        "label": "Patio Temperature",
        "chartType": "line",
        "legend": "false",
        "xformat": "HH:mm:ss",
        "interpolate": "linear",
        "nodata": "Awaiting Data",
        "dot": false,
        "ymin": "32",
        "ymax": "90",
        "removeOlder": "12",
        "removeOlderPoints": "",
        "removeOlderUnit": "3600",
        "cutout": 0,
        "useOneColor": false,
        "useUTC": false,
        "colors": [
            "#0bf0f4",
            "#aec7e8",
            "#ff7f0e",
            "#2ca02c",
            "#98df8a",
            "#d62728",
            "#ff9896",
            "#986ebf",
            "#c5b0d5"
        ],
        "outputs": 1,
        "useDifferentColor": false,
        "className": "",
        "x": 1040,
        "y": 660,
        "wires": [
            []
        ]
    },
    {
        "id": "d67a0ccda1a85141",
        "type": "function",
        "z": "fa36998f194a0113",
        "name": "Parse_into_devices_humidity",
        "func": "if (msg.payload.device_name) {\n    let hum = msg.payload.humidity;  // Store temperature first\n    let deviceName = msg.payload.device_name.toUpperCase();  // Convert to uppercase\n    msg.payload = hum;\n\n    switch (deviceName) {\n        case \"LIVINGROOM-C\":\n            return [msg, null, null];\n        case \"PATIO-B\":\n            return [null, msg, null];\n        case \"SHRINEROOM-A\":\n            return [null, null, msg];\n    }\nreturn null\n}",
        "outputs": 3,
        "timeout": 0,
        "noerr": 0,
        "initialize": "",
        "finalize": "",
        "libs": [],
        "x": 700,
        "y": 940,
        "wires": [
            [
                "e1c36f35f447b64e",
                "61a9d3d5901f60bc",
                "88417d6cdd8503df"
            ],
            [
                "e1c36f35f447b64e",
                "9189b7239fe54148",
                "d63d5aecc54c0c6f"
            ],
            [
                "e1c36f35f447b64e",
                "683a8535c06f1814",
                "7919224bb39cf692"
            ]
        ]
    },
    {
        "id": "e1c36f35f447b64e",
        "type": "debug",
        "z": "fa36998f194a0113",
        "name": "Humidity Data",
        "active": false,
        "tosidebar": true,
        "console": false,
        "tostatus": false,
        "complete": "payload",
        "targetType": "msg",
        "statusVal": "",
        "statusType": "auto",
        "x": 1020,
        "y": 940,
        "wires": []
    },
    {
        "id": "261066bba771706e",
        "type": "function",
        "z": "fa36998f194a0113",
        "name": "get_name_and_humidty",
        "func": "msg.payload = {\n    device_name: msg.payload.device_name,\n    humidity: msg.payload.humidity\n};\nreturn msg;\n",
        "outputs": 1,
        "timeout": 0,
        "noerr": 0,
        "initialize": "",
        "finalize": "",
        "libs": [],
        "x": 570,
        "y": 600,
        "wires": [
            [
                "542c8e8c7412980f",
                "d67a0ccda1a85141"
            ]
        ]
    },
    {
        "id": "542c8e8c7412980f",
        "type": "debug",
        "z": "fa36998f194a0113",
        "name": "Name and Humidit",
        "active": false,
        "tosidebar": true,
        "console": false,
        "tostatus": false,
        "complete": "payload",
        "targetType": "msg",
        "statusVal": "",
        "statusType": "auto",
        "x": 790,
        "y": 660,
        "wires": []
    },
    {
        "id": "61a9d3d5901f60bc",
        "type": "ui_gauge",
        "z": "fa36998f194a0113",
        "name": "LIVING ROOM HUMIDITY",
        "group": "976a565a31995234",
        "order": 4,
        "width": 0,
        "height": 0,
        "gtype": "gage",
        "title": "Living Room Humidity",
        "label": "%",
        "format": "{{value | number:0}}",
        "min": "0",
        "max": "100",
        "colors": [
            "#fc3503",
            "#09f505",
            "#d40ccd"
        ],
        "seg1": "50",
        "seg2": "75",
        "diff": false,
        "className": "",
        "x": 1050,
        "y": 1000,
        "wires": []
    },
    {
        "id": "88417d6cdd8503df",
        "type": "ui_chart",
        "z": "fa36998f194a0113",
        "name": "LIVING ROOM HUMIDITY",
        "group": "976a565a31995234",
        "order": 5,
        "width": 0,
        "height": 0,
        "label": "Living Room Humidity",
        "chartType": "line",
        "legend": "false",
        "xformat": "HH:mm:ss",
        "interpolate": "linear",
        "nodata": "Awaiting Data",
        "dot": false,
        "ymin": "0",
        "ymax": "100",
        "removeOlder": "12",
        "removeOlderPoints": "",
        "removeOlderUnit": "3600",
        "cutout": 0,
        "useOneColor": false,
        "useUTC": false,
        "colors": [
            "#a039f3",
            "#aec7e8",
            "#ff7f0e",
            "#2ca02c",
            "#98df8a",
            "#d62728",
            "#ff9896",
            "#986ebf",
            "#c5b0d5"
        ],
        "outputs": 1,
        "useDifferentColor": false,
        "className": "",
        "x": 1050,
        "y": 1040,
        "wires": [
            []
        ]
    },
    {
        "id": "9189b7239fe54148",
        "type": "ui_gauge",
        "z": "fa36998f194a0113",
        "name": "PATIO HUMIDITY",
        "group": "cf2742497e042c41",
        "order": 4,
        "width": 0,
        "height": 0,
        "gtype": "gage",
        "title": "Patio Humidity",
        "label": "%",
        "format": "{{value | number:0}}",
        "min": "0",
        "max": "100",
        "colors": [
            "#fc3503",
            "#09f505",
            "#d40ccd"
        ],
        "seg1": "50",
        "seg2": "75",
        "diff": false,
        "className": "",
        "x": 1030,
        "y": 1100,
        "wires": []
    },
    {
        "id": "d63d5aecc54c0c6f",
        "type": "ui_chart",
        "z": "fa36998f194a0113",
        "name": "PATIO HUMIDITY",
        "group": "cf2742497e042c41",
        "order": 5,
        "width": 0,
        "height": 0,
        "label": "Patio Humidity",
        "chartType": "line",
        "legend": "false",
        "xformat": "HH:mm:ss",
        "interpolate": "linear",
        "nodata": "Awaiting Data",
        "dot": false,
        "ymin": "0",
        "ymax": "100",
        "removeOlder": "12",
        "removeOlderPoints": "",
        "removeOlderUnit": "3600",
        "cutout": 0,
        "useOneColor": false,
        "useUTC": false,
        "colors": [
            "#a039f3",
            "#aec7e8",
            "#ff7f0e",
            "#2ca02c",
            "#98df8a",
            "#d62728",
            "#ff9896",
            "#986ebf",
            "#c5b0d5"
        ],
        "outputs": 1,
        "useDifferentColor": false,
        "className": "",
        "x": 1030,
        "y": 1140,
        "wires": [
            []
        ]
    },
    {
        "id": "683a8535c06f1814",
        "type": "ui_gauge",
        "z": "fa36998f194a0113",
        "name": "SHRINE ROOM HUMIDITY",
        "group": "a769dc138a6597bb",
        "order": 4,
        "width": 0,
        "height": 0,
        "gtype": "gage",
        "title": "Shrine Room Humidity",
        "label": "%",
        "format": "{{value | number:0}}",
        "min": "0",
        "max": "100",
        "colors": [
            "#fc3503",
            "#09f505",
            "#d40ccd"
        ],
        "seg1": "50",
        "seg2": "75",
        "diff": false,
        "className": "",
        "x": 1060,
        "y": 1200,
        "wires": []
    },
    {
        "id": "7919224bb39cf692",
        "type": "ui_chart",
        "z": "fa36998f194a0113",
        "name": "SHRINE ROOM HUMIDITY",
        "group": "a769dc138a6597bb",
        "order": 5,
        "width": 0,
        "height": 0,
        "label": "Shrine Room Humidity",
        "chartType": "line",
        "legend": "false",
        "xformat": "HH:mm:ss",
        "interpolate": "linear",
        "nodata": "Awaiting Data",
        "dot": false,
        "ymin": "0",
        "ymax": "100",
        "removeOlder": "12",
        "removeOlderPoints": "",
        "removeOlderUnit": "3600",
        "cutout": 0,
        "useOneColor": false,
        "useUTC": false,
        "colors": [
            "#a039f3",
            "#aec7e8",
            "#ff7f0e",
            "#2ca02c",
            "#98df8a",
            "#d62728",
            "#ff9896",
            "#986ebf",
            "#c5b0d5"
        ],
        "outputs": 1,
        "useDifferentColor": false,
        "className": "",
        "x": 1060,
        "y": 1240,
        "wires": [
            []
        ]
    },
    {
        "id": "2ad7c3d9ed7ce95b",
        "type": "function",
        "z": "fa36998f194a0113",
        "name": "get_timestamp",
        "func": "msg.payload = {\n    device_name: msg.payload.device_name,\n    time: msg.payload.time\n};\nreturn msg;",
        "outputs": 1,
        "timeout": 0,
        "noerr": 0,
        "initialize": "",
        "finalize": "",
        "libs": [],
        "x": 540,
        "y": 40,
        "wires": [
            [
                "8c2faa8c9f95804e",
                "01122749be475830"
            ]
        ]
    },
    {
        "id": "01122749be475830",
        "type": "debug",
        "z": "fa36998f194a0113",
        "name": "TimeStamp Debug",
        "active": false,
        "tosidebar": true,
        "console": false,
        "tostatus": false,
        "complete": "payload",
        "targetType": "msg",
        "statusVal": "",
        "statusType": "auto",
        "x": 770,
        "y": 40,
        "wires": []
    },
    {
        "id": "8c2faa8c9f95804e",
        "type": "function",
        "z": "fa36998f194a0113",
        "name": "Parse_into_devices_temperature",
        "func": "if (msg.payload.device_name) {\n    let time = msg.payload.time.substring(0, 16)\n    let deviceName = msg.payload.device_name.toUpperCase();  // Convert to uppercase\n    msg.payload = time;\n\n    switch (deviceName) {\n        case \"LIVINGROOM-C\":\n            return [msg, null, null, null];\n        case \"PATIO-B\":\n            return [null, msg, null, null];\n        case \"SHRINEROOM-A\":\n            return [null, null, msg, null];\n        case \"PORCH-B\":\n            return [null, null, null, msg];\n    }\n}\nreturn null;\n\n",
        "outputs": 4,
        "timeout": 0,
        "noerr": 0,
        "initialize": "",
        "finalize": "",
        "libs": [],
        "x": 720,
        "y": 140,
        "wires": [
            [
                "95c2a5acd4047954"
            ],
            [
                "8d4dd9034695c1d6"
            ],
            [
                "6c1d59b056ec4155"
            ],
            [
                "5de87a4db6e3df55"
            ]
        ]
    },
    {
        "id": "95c2a5acd4047954",
        "type": "ui_text",
        "z": "fa36998f194a0113",
        "group": "976a565a31995234",
        "order": 1,
        "width": 0,
        "height": 0,
        "name": "LIVING ROOM TIME",
        "label": "Time Updated",
        "format": "{{msg.payload}}",
        "layout": "col-center",
        "className": "",
        "style": false,
        "font": "",
        "fontSize": 16,
        "color": "#000000",
        "x": 1060,
        "y": 60,
        "wires": []
    },
    {
        "id": "8d4dd9034695c1d6",
        "type": "ui_text",
        "z": "fa36998f194a0113",
        "group": "cf2742497e042c41",
        "order": 1,
        "width": 0,
        "height": 0,
        "name": "PATIO TIME",
        "label": "Time Updated",
        "format": "{{msg.payload}}",
        "layout": "col-center",
        "className": "",
        "style": false,
        "font": "",
        "fontSize": 16,
        "color": "#000000",
        "x": 1030,
        "y": 100,
        "wires": []
    },
    {
        "id": "6c1d59b056ec4155",
        "type": "ui_text",
        "z": "fa36998f194a0113",
        "group": "a769dc138a6597bb",
        "order": 1,
        "width": 0,
        "height": 0,
        "name": "SHRINEROOM TIME",
        "label": "Time Updated",
        "format": "{{msg.payload}}",
        "layout": "col-center",
        "className": "",
        "style": false,
        "font": "",
        "fontSize": 16,
        "color": "#000000",
        "x": 1060,
        "y": 140,
        "wires": []
    },
    {
        "id": "5de87a4db6e3df55",
        "type": "ui_text",
        "z": "fa36998f194a0113",
        "group": "a7d03dcb5b95e73e",
        "order": 1,
        "width": 0,
        "height": 0,
        "name": "PORCH TIME",
        "label": "Time Updated",
        "format": "{{msg.payload}}",
        "layout": "col-center",
        "className": "",
        "style": false,
        "font": "",
        "fontSize": 16,
        "color": "#000000",
        "x": 1040,
        "y": 180,
        "wires": []
    },
    {
        "id": "702216e6785d70b6",
        "type": "mqtt in",
        "z": "388527266ba91c79",
        "name": "",
        "topic": "KTBMES/KTB_MBP/+/smartplugs/+/switch:0/#",
        "qos": "2",
        "datatype": "auto-detect",
        "broker": "40227b344b006862",
        "nl": false,
        "rap": true,
        "rh": 0,
        "inputs": 0,
        "x": 240,
        "y": 720,
        "wires": [
            [
                "625cfd7f1bf55aa7",
                "75398e3ed183e8f6",
                "2938a79d211175d1"
            ]
        ]
    },
    {
        "id": "625cfd7f1bf55aa7",
        "type": "debug",
        "z": "388527266ba91c79",
        "name": "debug 2",
        "active": false,
        "tosidebar": true,
        "console": false,
        "tostatus": false,
        "complete": "false",
        "statusVal": "",
        "statusType": "auto",
        "x": 600,
        "y": 520,
        "wires": []
    },
    {
        "id": "75398e3ed183e8f6",
        "type": "function",
        "z": "388527266ba91c79",
        "name": "Parse",
        "func": "// break out the input into (room, device, attribute, value)\n// output nodes:\n//  0 - office, lab, apower\n//  1 - office, lab, voltage\n//  2 - office, lab, current\n//  3 - office, lab, temperature\n//  4 - office, desk, apower\n//  5 - office, desk, voltage\n//  6 - office, desk, current\n//  7 - office, desk, temperature\n//  8 - garage, EV, apower\n//  9 - garage, EV, voltage\n// 10 - garage, EV, current\n// 11 - garage, EV, temperature\n\n// Split up the topic and ensure we have a valid topic string\nconst topicParts = msg.topic.split('/');\nif (topicParts.length < 3) {\n    node.warn(\"Invalid topic format: \" + msg.topic);\n    return null;\n}\n\n// topic string is expected to be in the format of\n//    [0]           [1]         [2]      [3]      [4]     [5]           [6]\n//   <root>/<publishing host>/<room>/smartplugs/<area>/switch:0/<attribute name>\n// and of course the payload is the value for the attribute\n\nconst room = topicParts[2]\nconst area = topicParts[4]\nconst attributeName = topicParts[topicParts.length - 1];\nconst attributeValue = String(msg.payload); // Convert payload to string\n\n// Helper function to create message array\nfunction createMessageArray(position, value) {\n    const arr = Array(12).fill(null);\n    if (value !== null) {\n        arr[position] = { payload: value };\n    }\n    return arr;\n}\n\nif (room === \"office\" && area === \"Shelly_Lab_01\") {\n    if (attributeName === \"apower\") {\n        return createMessageArray(0, attributeValue);\n    } else if (attributeName === \"voltage\") {\n        return createMessageArray(1, attributeValue);\n    } else if (attributeName === \"current\") {\n        return createMessageArray(2, attributeValue);\n    } else if (attributeName === \"tF\") {\n        return createMessageArray(3, attributeValue);\n    }\n} else if (room === \"office\" && area === \"Shelly_Prod\") {\n    if (attributeName === \"apower\") {\n        return createMessageArray(4, attributeValue);\n    } else if (attributeName === \"voltage\") {\n        return createMessageArray(5, attributeValue);\n    } else if (attributeName === \"current\") {\n        return createMessageArray(6, attributeValue);\n    } else if (attributeName === \"tF\") {\n        return createMessageArray(7, attributeValue);\n    }\n} else if (room === \"garage\" && area === \"Shelly_EV\") {\n    if (attributeName === \"apower\") {\n        return createMessageArray(8, attributeValue);\n    } else if (attributeName === \"voltage\") {\n        return createMessageArray(9, attributeValue);\n    } else if (attributeName === \"current\") {\n        return createMessageArray(10, attributeValue);\n    } else if (attributeName === \"tF\") {\n        return createMessageArray(11, attributeValue);\n    }\n} else {\n    node.warn(\"Invalid room/area: \" + room + \"/\" + area);\n    return null;\n}\n\n",
        "outputs": 12,
        "timeout": 0,
        "noerr": 0,
        "initialize": "",
        "finalize": "",
        "libs": [],
        "x": 590,
        "y": 720,
        "wires": [
            [
                "f9c0386217e52032",
                "b9b71ef06bc89fcc"
            ],
            [
                "d07fff6ea1694018",
                "d57ba8fbda8fe5da"
            ],
            [
                "dfc2267e5c65fab1",
                "e5d2731673ad35cd"
            ],
            [
                "59d99ceff27b727e",
                "221710d9d98c1799",
                "abe0786721a69dda"
            ],
            [
                "9120fb8a54108cbb",
                "75d85d03e14b1510"
            ],
            [
                "556704c922744bca",
                "66011082416a9408"
            ],
            [
                "75090361ebdc6316",
                "11283e8d7418d0b0"
            ],
            [
                "9ea89238d8921613",
                "6254be65c218dac8"
            ],
            [
                "cd118eaa800d82e4",
                "e422f2d3fbf2b286"
            ],
            [
                "06fb085ace1274c1",
                "a09e0eb6e2dc26c5"
            ],
            [
                "2a565ddfd8708ed3",
                "c448cda99d6ef4bb"
            ],
            [
                "634829ae3fcbf3a6",
                "0a7b1adb44632af8"
            ]
        ]
    },
    {
        "id": "221710d9d98c1799",
        "type": "debug",
        "z": "388527266ba91c79",
        "name": "debug 3",
        "active": false,
        "tosidebar": true,
        "console": false,
        "tostatus": false,
        "complete": "false",
        "statusVal": "",
        "statusType": "auto",
        "x": 640,
        "y": 560,
        "wires": []
    },
    {
        "id": "2938a79d211175d1",
        "type": "function",
        "z": "388527266ba91c79",
        "name": "Get TimeStamp",
        "func": "// Function to process MQTT messages and route based on device name\nfunction formatTimestamp(timestamp) {\n    console.log(\"Received timestamp:\", timestamp, \"Type:\", typeof timestamp);\n    \n    // Ensure we have a valid Date object\n    const date = new Date(Number(timestamp));\n    \n    if (isNaN(date.getTime())) {\n        console.log(\"Error: Invalid date created\");\n        return new Date().toLocaleString('en-US', {\n            timeZone: 'America/Los_Angeles',\n            year: 'numeric',\n            month: '2-digit',\n            day: '2-digit',\n            hour: '2-digit',\n            minute: '2-digit',\n            hour12: false\n        }).replace(/(\\d+)\\/(\\d+)\\/(\\d+),\\s+(\\d+:\\d+).*/, '$3-$1-$2 $4');\n    }\n    \n    return date.toLocaleString('en-US', {\n        timeZone: 'America/Los_Angeles',\n        year: 'numeric',\n        month: '2-digit',\n        day: '2-digit',\n        hour: '2-digit',\n        minute: '2-digit',\n        hour12: false\n    }).replace(/(\\d+)\\/(\\d+)\\/(\\d+),\\s+(\\d+:\\d+).*/, '$3-$1-$2  $4');\n}\n\n// Get the formatted timestamp from the message\nconst new_payload = formatTimestamp(msg.timestamp);\n\n// Split the topic into parts and get the device name (5th part)\nconst parts = msg.topic.split('/');\nconst device_name = parts[4] || '';\n\nlet output = [null, null, null];\n\n// Switch based on device_name\nmsg.payload = new_payload;\nswitch(device_name) {\n    case 'Shelly_Lab_01':\n        output[0] = msg;\n        break;\n    case 'Shelly_Prod':\n        output[1] = msg;\n        break;\n    case 'Shelly_EV':\n        output[2] = msg;\n        break;\n    // Default case already has all nulls\n}\n\n// Return the array of messages\nreturn output;\n",
        "outputs": 3,
        "timeout": 0,
        "noerr": 0,
        "initialize": "",
        "finalize": "",
        "libs": [],
        "x": 600,
        "y": 200,
        "wires": [
            [
                "977fe6c59bb99e5f",
                "6f2027ab8c441642",
                "168f853b9c6e8665"
            ],
            [
                "977fe6c59bb99e5f",
                "699d0c42c069407f",
                "7e5fe3c90095138e"
            ],
            [
                "977fe6c59bb99e5f",
                "092e85dc052a55d2",
                "626b50b87cfa7d3c"
            ]
        ]
    },
    {
        "id": "977fe6c59bb99e5f",
        "type": "debug",
        "z": "388527266ba91c79",
        "name": "debug 1",
        "active": false,
        "tosidebar": true,
        "console": false,
        "tostatus": false,
        "complete": "false",
        "statusVal": "",
        "statusType": "auto",
        "x": 640,
        "y": 60,
        "wires": []
    },
    {
        "id": "168f853b9c6e8665",
        "type": "ui_text",
        "z": "388527266ba91c79",
        "group": "551fa096c4be3b6d",
        "order": 1,
        "width": 0,
        "height": 0,
        "name": "Lab_Chart_Time",
        "label": "",
        "format": "{{msg.payload}}",
        "layout": "col-center",
        "className": "",
        "style": false,
        "font": "",
        "fontSize": 16,
        "color": "#000000",
        "x": 980,
        "y": 80,
        "wires": []
    },
    {
        "id": "699d0c42c069407f",
        "type": "ui_text",
        "z": "388527266ba91c79",
        "group": "b0aff1d8906e664d",
        "order": 1,
        "width": 0,
        "height": 0,
        "name": "Prod_Chart_Time",
        "label": "",
        "format": "{{msg.payload}}",
        "layout": "col-center",
        "className": "",
        "style": false,
        "font": "",
        "fontSize": 16,
        "color": "#000000",
        "x": 990,
        "y": 160,
        "wires": []
    },
    {
        "id": "092e85dc052a55d2",
        "type": "ui_text",
        "z": "388527266ba91c79",
        "group": "83a2dcafa4b40858",
        "order": 1,
        "width": 0,
        "height": 0,
        "name": "EV_Chart_Time",
        "label": "",
        "format": "{{msg.payload}}",
        "layout": "col-center",
        "className": "",
        "style": false,
        "font": "",
        "fontSize": 16,
        "color": "#000000",
        "x": 980,
        "y": 240,
        "wires": []
    },
    {
        "id": "6f2027ab8c441642",
        "type": "ui_text",
        "z": "388527266ba91c79",
        "group": "342e62fb87e28291",
        "order": 1,
        "width": 0,
        "height": 0,
        "name": "Lab_Guage_Time",
        "label": "",
        "format": "{{msg.payload}}",
        "layout": "col-center",
        "className": "",
        "style": false,
        "font": "",
        "fontSize": 16,
        "color": "#000000",
        "x": 990,
        "y": 120,
        "wires": []
    },
    {
        "id": "7e5fe3c90095138e",
        "type": "ui_text",
        "z": "388527266ba91c79",
        "group": "0120b7d51f39933f",
        "order": 1,
        "width": 0,
        "height": 0,
        "name": "Prod_Guage_Time",
        "label": "",
        "format": "{{msg.payload}}",
        "layout": "col-center",
        "className": "",
        "style": false,
        "font": "",
        "fontSize": 16,
        "color": "#000000",
        "x": 990,
        "y": 200,
        "wires": []
    },
    {
        "id": "626b50b87cfa7d3c",
        "type": "ui_text",
        "z": "388527266ba91c79",
        "group": "d0e6d933f5c08d05",
        "order": 1,
        "width": 0,
        "height": 0,
        "name": "EV_Guage_Time",
        "label": "",
        "format": "{{msg.payload}}",
        "layout": "col-center",
        "className": "",
        "style": false,
        "font": "",
        "fontSize": 16,
        "color": "#000000",
        "x": 980,
        "y": 280,
        "wires": []
    },
    {
        "id": "f9c0386217e52032",
        "type": "ui_gauge",
        "z": "388527266ba91c79",
        "name": "Lab aPower",
        "group": "342e62fb87e28291",
        "order": 2,
        "width": 0,
        "height": 0,
        "gtype": "gage",
        "title": "Lab aPower",
        "label": "Watts",
        "format": "{{value}}",
        "min": 0,
        "max": "200",
        "colors": [
            "#00b500",
            "#e6e600",
            "#ca3838"
        ],
        "seg1": "35",
        "seg2": "75",
        "diff": false,
        "className": "",
        "x": 970,
        "y": 380,
        "wires": []
    },
    {
        "id": "d07fff6ea1694018",
        "type": "ui_gauge",
        "z": "388527266ba91c79",
        "name": "Lab Voltage",
        "group": "342e62fb87e28291",
        "order": 4,
        "width": 0,
        "height": 0,
        "gtype": "gage",
        "title": "Lab Voltage",
        "label": "Volts",
        "format": "{{value}}",
        "min": 0,
        "max": "130",
        "colors": [
            "#b09303",
            "#01b500",
            "#ca3838"
        ],
        "seg1": "100",
        "seg2": "125",
        "diff": true,
        "className": "",
        "x": 970,
        "y": 460,
        "wires": []
    },
    {
        "id": "dfc2267e5c65fab1",
        "type": "ui_gauge",
        "z": "388527266ba91c79",
        "name": "Lab Current",
        "group": "342e62fb87e28291",
        "order": 3,
        "width": 0,
        "height": 0,
        "gtype": "gage",
        "title": "Lab Current",
        "label": "Amps",
        "format": "{{value}}",
        "min": 0,
        "max": 10,
        "colors": [
            "#00b500",
            "#e6e600",
            "#ca3838"
        ],
        "seg1": "10",
        "seg2": "12",
        "diff": false,
        "className": "",
        "x": 970,
        "y": 540,
        "wires": []
    },
    {
        "id": "59d99ceff27b727e",
        "type": "ui_gauge",
        "z": "388527266ba91c79",
        "name": "Lab Temperature",
        "group": "342e62fb87e28291",
        "order": 5,
        "width": 0,
        "height": 0,
        "gtype": "gage",
        "title": "Lab Temperature",
        "label": "degrees F",
        "format": "{{value}}",
        "min": "30",
        "max": "200",
        "colors": [
            "#0490fb",
            "#f9de58",
            "#ca3838"
        ],
        "seg1": "120",
        "seg2": "180",
        "diff": false,
        "className": "",
        "x": 990,
        "y": 620,
        "wires": []
    },
    {
        "id": "e422f2d3fbf2b286",
        "type": "ui_gauge",
        "z": "388527266ba91c79",
        "name": "EV aPower",
        "group": "d0e6d933f5c08d05",
        "order": 2,
        "width": 0,
        "height": 0,
        "gtype": "gage",
        "title": "EV aPower",
        "label": "Watts",
        "format": "{{value}}",
        "min": 0,
        "max": "200",
        "colors": [
            "#00b500",
            "#e6e600",
            "#ca3838"
        ],
        "seg1": "35",
        "seg2": "75",
        "diff": false,
        "className": "",
        "x": 970,
        "y": 1060,
        "wires": []
    },
    {
        "id": "a09e0eb6e2dc26c5",
        "type": "ui_gauge",
        "z": "388527266ba91c79",
        "name": "EV Voltage",
        "group": "d0e6d933f5c08d05",
        "order": 4,
        "width": 0,
        "height": 0,
        "gtype": "gage",
        "title": "EV Voltage",
        "label": "Volts",
        "format": "{{value}}",
        "min": 0,
        "max": "130",
        "colors": [
            "#b09303",
            "#01b500",
            "#ca3838"
        ],
        "seg1": "100",
        "seg2": "125",
        "diff": true,
        "className": "",
        "x": 970,
        "y": 1140,
        "wires": []
    },
    {
        "id": "c448cda99d6ef4bb",
        "type": "ui_gauge",
        "z": "388527266ba91c79",
        "name": "EV Current",
        "group": "d0e6d933f5c08d05",
        "order": 3,
        "width": 0,
        "height": 0,
        "gtype": "gage",
        "title": "EV Current",
        "label": "Amps",
        "format": "{{value}}",
        "min": 0,
        "max": 10,
        "colors": [
            "#00b500",
            "#e6e600",
            "#ca3838"
        ],
        "seg1": "10",
        "seg2": "12",
        "diff": false,
        "className": "",
        "x": 970,
        "y": 1220,
        "wires": []
    },
    {
        "id": "0a7b1adb44632af8",
        "type": "ui_gauge",
        "z": "388527266ba91c79",
        "name": "EV Temperature",
        "group": "d0e6d933f5c08d05",
        "order": 5,
        "width": 0,
        "height": 0,
        "gtype": "gage",
        "title": "EV Temperature",
        "label": "degrees F",
        "format": "{{value}}",
        "min": 0,
        "max": "200",
        "colors": [
            "#0490fb",
            "#f9de58",
            "#ca3838"
        ],
        "seg1": "120",
        "seg2": "180",
        "diff": false,
        "className": "",
        "x": 980,
        "y": 1300,
        "wires": []
    },
    {
        "id": "9120fb8a54108cbb",
        "type": "ui_gauge",
        "z": "388527266ba91c79",
        "name": "Prod aPower",
        "group": "0120b7d51f39933f",
        "order": 2,
        "width": 0,
        "height": 0,
        "gtype": "gage",
        "title": "Prod aPower",
        "label": "Watts",
        "format": "{{value}}",
        "min": 0,
        "max": "200",
        "colors": [
            "#00b500",
            "#e6e600",
            "#ca3838"
        ],
        "seg1": "35",
        "seg2": "75",
        "diff": false,
        "className": "",
        "x": 970,
        "y": 720,
        "wires": []
    },
    {
        "id": "556704c922744bca",
        "type": "ui_gauge",
        "z": "388527266ba91c79",
        "name": "Prod Voltage",
        "group": "0120b7d51f39933f",
        "order": 4,
        "width": 0,
        "height": 0,
        "gtype": "gage",
        "title": "Prod Voltage",
        "label": "Volts",
        "format": "{{value}}",
        "min": 0,
        "max": "130",
        "colors": [
            "#b09303",
            "#01b500",
            "#ca3838"
        ],
        "seg1": "100",
        "seg2": "125",
        "diff": true,
        "className": "",
        "x": 970,
        "y": 800,
        "wires": []
    },
    {
        "id": "75090361ebdc6316",
        "type": "ui_gauge",
        "z": "388527266ba91c79",
        "name": "Prod Current",
        "group": "0120b7d51f39933f",
        "order": 3,
        "width": 0,
        "height": 0,
        "gtype": "gage",
        "title": "Prod Current",
        "label": "Amps",
        "format": "{{value}}",
        "min": 0,
        "max": 10,
        "colors": [
            "#00b500",
            "#e6e600",
            "#ca3838"
        ],
        "seg1": "10",
        "seg2": "12",
        "diff": false,
        "className": "",
        "x": 970,
        "y": 880,
        "wires": []
    },
    {
        "id": "9ea89238d8921613",
        "type": "ui_gauge",
        "z": "388527266ba91c79",
        "name": "Prod Temperature",
        "group": "0120b7d51f39933f",
        "order": 5,
        "width": 0,
        "height": 0,
        "gtype": "gage",
        "title": "Prod Temperature",
        "label": "degrees F",
        "format": "{{value}}",
        "min": 0,
        "max": "200",
        "colors": [
            "#0490fb",
            "#f9de58",
            "#ca3838"
        ],
        "seg1": "120",
        "seg2": "180",
        "diff": false,
        "className": "",
        "x": 990,
        "y": 960,
        "wires": []
    },
    {
        "id": "b9b71ef06bc89fcc",
        "type": "ui_chart",
        "z": "388527266ba91c79",
        "name": "Lab aPower",
        "group": "551fa096c4be3b6d",
        "order": 2,
        "width": 0,
        "height": 0,
        "label": "Lab aPower",
        "chartType": "line",
        "legend": "false",
        "xformat": "HH:mm:ss",
        "interpolate": "linear",
        "nodata": "No Data Yet",
        "dot": false,
        "ymin": "0",
        "ymax": "200",
        "removeOlder": "12",
        "removeOlderPoints": "",
        "removeOlderUnit": "3600",
        "cutout": 0,
        "useOneColor": false,
        "useUTC": false,
        "colors": [
            "#1f77b4",
            "#aec7e8",
            "#ff7f0e",
            "#2ca02c",
            "#98df8a",
            "#d62728",
            "#ff9896",
            "#9467bd",
            "#c5b0d5"
        ],
        "outputs": 1,
        "useDifferentColor": false,
        "className": "",
        "x": 970,
        "y": 420,
        "wires": [
            []
        ]
    },
    {
        "id": "d57ba8fbda8fe5da",
        "type": "ui_chart",
        "z": "388527266ba91c79",
        "name": "Lab Voltage",
        "group": "551fa096c4be3b6d",
        "order": 6,
        "width": 0,
        "height": 0,
        "label": "Lab Voltage",
        "chartType": "line",
        "legend": "false",
        "xformat": "HH:mm:ss",
        "interpolate": "linear",
        "nodata": "No Data Yet",
        "dot": false,
        "ymin": "0",
        "ymax": "130",
        "removeOlder": "12",
        "removeOlderPoints": "",
        "removeOlderUnit": "3600",
        "cutout": 0,
        "useOneColor": false,
        "useUTC": false,
        "colors": [
            "#ffd500",
            "#aec7e8",
            "#ff7f0e",
            "#2ca02c",
            "#98df8a",
            "#d62728",
            "#ff9896",
            "#9467bd",
            "#ffff00"
        ],
        "outputs": 1,
        "useDifferentColor": false,
        "className": "",
        "x": 970,
        "y": 500,
        "wires": [
            []
        ]
    },
    {
        "id": "e5d2731673ad35cd",
        "type": "ui_chart",
        "z": "388527266ba91c79",
        "name": "Lab Current",
        "group": "551fa096c4be3b6d",
        "order": 4,
        "width": 0,
        "height": 0,
        "label": "Lab Current",
        "chartType": "line",
        "legend": "false",
        "xformat": "HH:mm:ss",
        "interpolate": "linear",
        "nodata": "No Data Yet",
        "dot": false,
        "ymin": "0",
        "ymax": "15",
        "removeOlder": "12",
        "removeOlderPoints": "",
        "removeOlderUnit": "3600",
        "cutout": 0,
        "useOneColor": false,
        "useUTC": false,
        "colors": [
            "#00ff40",
            "#aec7e8",
            "#ff7f0e",
            "#2ca02c",
            "#98df8a",
            "#d62728",
            "#ff9896",
            "#9467bd",
            "#ffff00"
        ],
        "outputs": 1,
        "useDifferentColor": false,
        "className": "",
        "x": 970,
        "y": 580,
        "wires": [
            []
        ]
    },
    {
        "id": "abe0786721a69dda",
        "type": "ui_chart",
        "z": "388527266ba91c79",
        "name": "Lab Temperature",
        "group": "551fa096c4be3b6d",
        "order": 8,
        "width": 0,
        "height": 0,
        "label": "Lab Temperature",
        "chartType": "line",
        "legend": "false",
        "xformat": "HH:mm:ss",
        "interpolate": "linear",
        "nodata": "No Data Yet",
        "dot": false,
        "ymin": "30",
        "ymax": "150",
        "removeOlder": "12",
        "removeOlderPoints": "",
        "removeOlderUnit": "3600",
        "cutout": 0,
        "useOneColor": false,
        "useUTC": false,
        "colors": [
            "#0055ff",
            "#aec7e8",
            "#ff7f0e",
            "#2ca02c",
            "#98df8a",
            "#d62728",
            "#ff9896",
            "#9467bd",
            "#ffff00"
        ],
        "outputs": 1,
        "useDifferentColor": false,
        "className": "",
        "x": 990,
        "y": 660,
        "wires": [
            []
        ]
    },
    {
        "id": "cd118eaa800d82e4",
        "type": "ui_chart",
        "z": "388527266ba91c79",
        "name": "EV aPower",
        "group": "83a2dcafa4b40858",
        "order": 2,
        "width": 0,
        "height": 0,
        "label": "EV aPower",
        "chartType": "line",
        "legend": "false",
        "xformat": "HH:mm:ss",
        "interpolate": "linear",
        "nodata": "No Data Yet",
        "dot": false,
        "ymin": "0",
        "ymax": "200",
        "removeOlder": "24",
        "removeOlderPoints": "",
        "removeOlderUnit": "3600",
        "cutout": 0,
        "useOneColor": false,
        "useUTC": false,
        "colors": [
            "#1f77b4",
            "#aec7e8",
            "#ff7f0e",
            "#2ca02c",
            "#98df8a",
            "#d62728",
            "#ff9896",
            "#9467bd",
            "#c5b0d5"
        ],
        "outputs": 1,
        "useDifferentColor": false,
        "className": "",
        "x": 970,
        "y": 1100,
        "wires": [
            []
        ]
    },
    {
        "id": "06fb085ace1274c1",
        "type": "ui_chart",
        "z": "388527266ba91c79",
        "name": "EV Voltage",
        "group": "83a2dcafa4b40858",
        "order": 6,
        "width": 0,
        "height": 0,
        "label": "EV Voltage",
        "chartType": "line",
        "legend": "false",
        "xformat": "HH:mm:ss",
        "interpolate": "linear",
        "nodata": "No Data Yet",
        "dot": false,
        "ymin": "0",
        "ymax": "130",
        "removeOlder": "12",
        "removeOlderPoints": "",
        "removeOlderUnit": "3600",
        "cutout": 0,
        "useOneColor": false,
        "useUTC": false,
        "colors": [
            "#ffd500",
            "#aec7e8",
            "#ff7f0e",
            "#2ca02c",
            "#98df8a",
            "#d62728",
            "#ff9896",
            "#9467bd",
            "#ffff00"
        ],
        "outputs": 1,
        "useDifferentColor": false,
        "className": "",
        "x": 970,
        "y": 1180,
        "wires": [
            []
        ]
    },
    {
        "id": "2a565ddfd8708ed3",
        "type": "ui_chart",
        "z": "388527266ba91c79",
        "name": "EV Current",
        "group": "83a2dcafa4b40858",
        "order": 4,
        "width": 0,
        "height": 0,
        "label": "EV Current",
        "chartType": "line",
        "legend": "false",
        "xformat": "HH:mm:ss",
        "interpolate": "linear",
        "nodata": "No Data Yet",
        "dot": false,
        "ymin": "0",
        "ymax": "15",
        "removeOlder": "12",
        "removeOlderPoints": "",
        "removeOlderUnit": "3600",
        "cutout": 0,
        "useOneColor": false,
        "useUTC": false,
        "colors": [
            "#00ff40",
            "#aec7e8",
            "#ff7f0e",
            "#2ca02c",
            "#98df8a",
            "#d62728",
            "#ff9896",
            "#9467bd",
            "#ffff00"
        ],
        "outputs": 1,
        "useDifferentColor": false,
        "className": "",
        "x": 970,
        "y": 1260,
        "wires": [
            []
        ]
    },
    {
        "id": "634829ae3fcbf3a6",
        "type": "ui_chart",
        "z": "388527266ba91c79",
        "name": "EV Temperature",
        "group": "83a2dcafa4b40858",
        "order": 8,
        "width": 0,
        "height": 0,
        "label": "EV Temperature",
        "chartType": "line",
        "legend": "false",
        "xformat": "HH:mm:ss",
        "interpolate": "linear",
        "nodata": "No Data Yet",
        "dot": false,
        "ymin": "30",
        "ymax": "150",
        "removeOlder": "12",
        "removeOlderPoints": "",
        "removeOlderUnit": "3600",
        "cutout": 0,
        "useOneColor": false,
        "useUTC": false,
        "colors": [
            "#0055ff",
            "#aec7e8",
            "#ff7f0e",
            "#2ca02c",
            "#98df8a",
            "#d62728",
            "#ff9896",
            "#9467bd",
            "#ffff00"
        ],
        "outputs": 1,
        "useDifferentColor": false,
        "className": "",
        "x": 980,
        "y": 1340,
        "wires": [
            []
        ]
    },
    {
        "id": "75d85d03e14b1510",
        "type": "ui_chart",
        "z": "388527266ba91c79",
        "name": "Prod aPower",
        "group": "b0aff1d8906e664d",
        "order": 2,
        "width": 0,
        "height": 0,
        "label": "Prod aPower",
        "chartType": "line",
        "legend": "false",
        "xformat": "HH:mm:ss",
        "interpolate": "linear",
        "nodata": "No Data Yet",
        "dot": false,
        "ymin": "0",
        "ymax": "200",
        "removeOlder": "12",
        "removeOlderPoints": "",
        "removeOlderUnit": "3600",
        "cutout": 0,
        "useOneColor": false,
        "useUTC": false,
        "colors": [
            "#1f77b4",
            "#aec7e8",
            "#ff7f0e",
            "#2ca02c",
            "#98df8a",
            "#d62728",
            "#ff9896",
            "#9467bd",
            "#c5b0d5"
        ],
        "outputs": 1,
        "useDifferentColor": false,
        "className": "",
        "x": 970,
        "y": 760,
        "wires": [
            []
        ]
    },
    {
        "id": "66011082416a9408",
        "type": "ui_chart",
        "z": "388527266ba91c79",
        "name": "Prod Voltage",
        "group": "b0aff1d8906e664d",
        "order": 6,
        "width": 0,
        "height": 0,
        "label": "Prod Voltage",
        "chartType": "line",
        "legend": "false",
        "xformat": "HH:mm:ss",
        "interpolate": "linear",
        "nodata": "No Data Yet",
        "dot": false,
        "ymin": "0",
        "ymax": "130",
        "removeOlder": "12",
        "removeOlderPoints": "",
        "removeOlderUnit": "3600",
        "cutout": 0,
        "useOneColor": false,
        "useUTC": false,
        "colors": [
            "#ffd500",
            "#aec7e8",
            "#ff7f0e",
            "#2ca02c",
            "#98df8a",
            "#d62728",
            "#ff9896",
            "#9467bd",
            "#ffff00"
        ],
        "outputs": 1,
        "useDifferentColor": false,
        "className": "",
        "x": 970,
        "y": 840,
        "wires": [
            []
        ]
    },
    {
        "id": "11283e8d7418d0b0",
        "type": "ui_chart",
        "z": "388527266ba91c79",
        "name": "Prod Current",
        "group": "b0aff1d8906e664d",
        "order": 4,
        "width": 0,
        "height": 0,
        "label": "Prod Current",
        "chartType": "line",
        "legend": "false",
        "xformat": "HH:mm:ss",
        "interpolate": "linear",
        "nodata": "No Data Yet",
        "dot": false,
        "ymin": "0",
        "ymax": "15",
        "removeOlder": "12",
        "removeOlderPoints": "",
        "removeOlderUnit": "3600",
        "cutout": 0,
        "useOneColor": false,
        "useUTC": false,
        "colors": [
            "#00ff40",
            "#aec7e8",
            "#ff7f0e",
            "#2ca02c",
            "#98df8a",
            "#d62728",
            "#ff9896",
            "#9467bd",
            "#ffff00"
        ],
        "outputs": 1,
        "useDifferentColor": false,
        "className": "",
        "x": 970,
        "y": 920,
        "wires": [
            []
        ]
    },
    {
        "id": "6254be65c218dac8",
        "type": "ui_chart",
        "z": "388527266ba91c79",
        "name": "Prod Temperature",
        "group": "b0aff1d8906e664d",
        "order": 8,
        "width": 0,
        "height": 0,
        "label": "Prod Temperature",
        "chartType": "line",
        "legend": "false",
        "xformat": "HH:mm:ss",
        "interpolate": "linear",
        "nodata": "No Data Yet",
        "dot": false,
        "ymin": "30",
        "ymax": "150",
        "removeOlder": "12",
        "removeOlderPoints": "",
        "removeOlderUnit": "3600",
        "cutout": 0,
        "useOneColor": false,
        "useUTC": false,
        "colors": [
            "#0055ff",
            "#aec7e8",
            "#ff7f0e",
            "#2ca02c",
            "#98df8a",
            "#d62728",
            "#ff9896",
            "#9467bd",
            "#ffff00"
        ],
        "outputs": 1,
        "useDifferentColor": false,
        "className": "",
        "x": 990,
        "y": 1000,
        "wires": [
            []
        ]
    }
]